AtomProNet/MLIP_post_processing.py
AtomProNet/VASP_convergence_check.py
AtomProNet/__init__.py
AtomProNet/atom_symbol.py
AtomProNet/combine.py
AtomProNet/energy.py
AtomProNet/lattice.py
AtomProNet/materials_project.py
AtomProNet/nequip_to_mace.py
AtomProNet/npz_to_extxyz.py
AtomProNet/organize.py
AtomProNet/position_force.py
AtomProNet/pressure_eV.py
AtomProNet/process_and_run_script.py
AtomProNet/process_and_run_script_legacy_version.py
AtomProNet/split.py
AtomProNet/tests/__init__.py
AtomProNet/tests/atom_symbol.py
AtomProNet/tests/combine.py
AtomProNet/tests/energy.py
AtomProNet/tests/lattice.py
AtomProNet/tests/npz_to_extxyz.py
AtomProNet/tests/position_force.py
AtomProNet/tests/pressure_eV.py
AtomProNet/tests/test_process_and_run_script.py
AtomProNet-0.0.1.dist-info/LICENSE
AtomProNet-0.0.1.dist-info/METADATA
AtomProNet-0.0.1.dist-info/WHEEL
AtomProNet-0.0.1.dist-info/entry_points.txt
AtomProNet-0.0.1.dist-info/top_level.txt
AtomProNet-0.0.1.dist-info/RECORD
