Metadata-Version: 2.2
Name: AtomProNet
Version: 0.0.1
Summary: A Python package for pre and post-process VASP/Quantum ESPRESSO data into machine learning interatomic potential (MLIP) format.
Home-page: https://github.com/MusannaGalib/AtomProNet
Author: Musanna Galib
Author-email: galibubc@student.ubc.ca
Classifier: Development Status :: 5 - Production/Stable
Classifier: Intended Audience :: Science/Research
Classifier: License :: OSI Approved :: MIT License
Classifier: Programming Language :: Python :: 3
Requires-Python: >=3.6
License-File: LICENSE
Requires-Dist: numpy
Requires-Dist: ase
Requires-Dist: mp-api
Requires-Dist: scipy
Requires-Dist: pymatgen==2023.11.12
Requires-Dist: statsmodels
Requires-Dist: seaborn
Requires-Dist: scikit-learn
Dynamic: author
Dynamic: author-email
Dynamic: classifier
Dynamic: description
Dynamic: description-content-type
Dynamic: home-page
Dynamic: requires-dist
Dynamic: requires-python
Dynamic: summary
